munter/__init__.py
munter/__main__.py
munter/gui.py
munter/munter.py
munter.py-2.3.0.dist-info/LICENSE
munter.py-2.3.0.dist-info/METADATA
munter.py-2.3.0.dist-info/WHEEL
munter.py-2.3.0.dist-info/entry_points.txt
munter.py-2.3.0.dist-info/top_level.txt
munter.py-2.3.0.dist-info/RECORD
