Metadata-Version: 2.1
Name: munter.py
Version: 2.3.0
Summary: An easy-to-use implementation of the Munter time calculation
Home-page: https://wylark.com/munter
Author: Alexander Vasarab
Author-email: alexander@wylark.com
License: ISC
Project-URL: Source Code, https://wylark.com/git/munter.git
Keywords: munter,tour planning,trip planning,time estimate
Platform: UNKNOWN
Classifier: Development Status :: 5 - Production/Stable
Classifier: Environment :: Console
Classifier: Intended Audience :: Other Audience
Classifier: Intended Audience :: Developers
Classifier: Natural Language :: English
Classifier: License :: OSI Approved :: ISC License (ISCL)
Classifier: Programming Language :: Python :: 3 :: Only
Classifier: Programming Language :: Python :: 3
Classifier: Programming Language :: Python :: 3.6
Classifier: Programming Language :: Python :: 3.7
Classifier: Programming Language :: Python :: 3.8
Classifier: Programming Language :: Python
Classifier: Topic :: Software Development
Classifier: Topic :: Software Development :: Libraries :: Python Modules
Requires-Python: >=3.6
